<pnp:Navigation xmlns:pnp="http://schemas.dev.office.com/PnP/2022/09/ProvisioningSchema">

  <pnp:CurrentNavigation>
    <pnp:StructuralNavigation RemoveExistingNodes="false">

      <!-- Home Page -->
      <pnp:NavigationNode Title="Home"
                          Url="/SitePages/Home.aspx"
                          IsExternal="false" />

      <!-- Dashboards Node -->
      <pnp:NavigationNode Title="Dashboards" Url="" IsExternal="false">

        <pnp:NavigationNode Title="My Requests"
                            Url="/SitePages/MyRequestsDashboard.aspx"
                            IsExternal="false" />

        <pnp:NavigationNode Title="Legal Admin"
                            Url="/SitePages/LegalAdminDashboard.aspx"
                            IsExternal="false" />

        <pnp:NavigationNode Title="Attorney Assignment"
                            Url="/SitePages/AttorneyAssignmentDashboard.aspx"
                            IsExternal="false" />

        <pnp:NavigationNode Title="Attorney Reviews"
                            Url="/SitePages/AttorneyDashboard.aspx"
                            IsExternal="false" />

        <pnp:NavigationNode Title="Compliance Reviews"
                            Url="/SitePages/ComplianceDashboard.aspx"
                            IsExternal="false" />

      </pnp:NavigationNode>

      <!-- Requests List -->
      <pnp:NavigationNode Title="All Requests"
                          Url="/Lists/Requests/AllItems.aspx"
                          IsExternal="false" />

    </pnp:StructuralNavigation>
  </pnp:CurrentNavigation>

</pnp:Navigation>
